{"name":"Colin views the details for specific products","id":"browse-the-catalog;colin-views-the-details-for-specific-products","testSteps":[{"number":1,"description":"1: Colin views the details for specific products ({Product Name\u003dSauce Labs Backpack, Price\u003d$29.99, Description\u003dcarry.allTheThings()})","duration":4160,"startTime":"2021-12-22T04:12:09.505426384Z[Etc/UTC]","screenshots":[{"screenshot":"1bd1268f1e1be5f3bf96bd82ecbea1d53f437139494bd2415be950dd44c0cc85.png","timeStamp":1640146330002},{"screenshot":"d508765a4a5bf8da1a6097a20f84cac5799a28ae3c8ee226ec337bf91493d23f.png","timeStamp":1640146333666}],"result":"SUCCESS","precondition":false,"level":0,"lineNumber":50,"children":[{"number":2,"description":"Given Colin has logged onto the application","duration":538,"startTime":"2021-12-22T04:12:10.009740872Z[Etc/UTC]","screenshots":[{"screenshot":"1bd1268f1e1be5f3bf96bd82ecbea1d53f437139494bd2415be950dd44c0cc85.png","timeStamp":1640146330011},{"screenshot":"1bd1268f1e1be5f3bf96bd82ecbea1d53f437139494bd2415be950dd44c0cc85.png","timeStamp":1640146330547}],"result":"SUCCESS","precondition":false,"level":1},{"number":3,"description":"Given Colin is browsing the product catalog","duration":1225,"startTime":"2021-12-22T04:12:10.549108552Z[Etc/UTC]","screenshots":[{"screenshot":"1bd1268f1e1be5f3bf96bd82ecbea1d53f437139494bd2415be950dd44c0cc85.png","timeStamp":1640146330550},{"screenshot":"1bd1268f1e1be5f3bf96bd82ecbea1d53f437139494bd2415be950dd44c0cc85.png","timeStamp":1640146331774}],"result":"SUCCESS","precondition":false,"level":1,"children":[{"number":4,"description":"Colin opens the https://www.saucedemo.com/inventory.html","duration":1216,"startTime":"2021-12-22T04:12:10.554376975Z[Etc/UTC]","screenshots":[{"screenshot":"1bd1268f1e1be5f3bf96bd82ecbea1d53f437139494bd2415be950dd44c0cc85.png","timeStamp":1640146330574},{"screenshot":"1bd1268f1e1be5f3bf96bd82ecbea1d53f437139494bd2415be950dd44c0cc85.png","timeStamp":1640146331770}],"result":"SUCCESS","precondition":false,"level":2}]},{"number":5,"description":"When Colin opens the product details for \"Sauce Labs Backpack\"","duration":746,"startTime":"2021-12-22T04:12:11.779745408Z[Etc/UTC]","screenshots":[{"screenshot":"1bd1268f1e1be5f3bf96bd82ecbea1d53f437139494bd2415be950dd44c0cc85.png","timeStamp":1640146331783},{"screenshot":"d508765a4a5bf8da1a6097a20f84cac5799a28ae3c8ee226ec337bf91493d23f.png","timeStamp":1640146332526}],"result":"SUCCESS","precondition":false,"level":1,"children":[{"number":6,"description":"Colin clicks on the \u0027Sauce Labs Backpack\u0027 link","duration":733,"startTime":"2021-12-22T04:12:11.789767763Z[Etc/UTC]","screenshots":[{"screenshot":"1bd1268f1e1be5f3bf96bd82ecbea1d53f437139494bd2415be950dd44c0cc85.png","timeStamp":1640146331792},{"screenshot":"d508765a4a5bf8da1a6097a20f84cac5799a28ae3c8ee226ec337bf91493d23f.png","timeStamp":1640146332523}],"result":"SUCCESS","precondition":false,"level":2}]},{"number":7,"description":"Then he should see a product with the following details:\n| Name | Price | Description |\n| Sauce Labs Backpack | $29.99 | carry.allTheThings() |","duration":1136,"startTime":"2021-12-22T04:12:12.526626079Z[Etc/UTC]","screenshots":[{"screenshot":"d508765a4a5bf8da1a6097a20f84cac5799a28ae3c8ee226ec337bf91493d23f.png","timeStamp":1640146332528},{"screenshot":"d508765a4a5bf8da1a6097a20f84cac5799a28ae3c8ee226ec337bf91493d23f.png","timeStamp":1640146333663}],"result":"SUCCESS","precondition":false,"level":1,"children":[{"number":8,"description":"he should see the \u0027inventory_details_name\u0027 element with text value that is equal to (ignoring case): \u003c\"Sauce Labs Backpack\"\u003e","duration":35,"startTime":"2021-12-22T04:12:12.533744776Z[Etc/UTC]","screenshots":[{"screenshot":"d508765a4a5bf8da1a6097a20f84cac5799a28ae3c8ee226ec337bf91493d23f.png","timeStamp":1640146332536},{"screenshot":"d508765a4a5bf8da1a6097a20f84cac5799a28ae3c8ee226ec337bf91493d23f.png","timeStamp":1640146332568}],"result":"SUCCESS","precondition":false,"level":2},{"number":9,"description":"he should see the \u0027inventory_details_price\u0027 element with text content that is equal to: \u003c\"$29.99\"\u003e","duration":553,"startTime":"2021-12-22T04:12:12.581239088Z[Etc/UTC]","screenshots":[{"screenshot":"d508765a4a5bf8da1a6097a20f84cac5799a28ae3c8ee226ec337bf91493d23f.png","timeStamp":1640146333085},{"screenshot":"d508765a4a5bf8da1a6097a20f84cac5799a28ae3c8ee226ec337bf91493d23f.png","timeStamp":1640146333134}],"result":"SUCCESS","precondition":false,"level":2},{"number":10,"description":"he should see the \u0027inventory_details_desc\u0027 element with text value that contains: \u003c[carry.allTheThings()]\u003e","duration":521,"startTime":"2021-12-22T04:12:13.137608721Z[Etc/UTC]","screenshots":[{"screenshot":"d508765a4a5bf8da1a6097a20f84cac5799a28ae3c8ee226ec337bf91493d23f.png","timeStamp":1640146333619},{"screenshot":"d508765a4a5bf8da1a6097a20f84cac5799a28ae3c8ee226ec337bf91493d23f.png","timeStamp":1640146333659}],"result":"SUCCESS","precondition":false,"level":2}]}]},{"number":11,"description":"2: Colin views the details for specific products ({Product Name\u003dSauce Labs Bike Light, Price\u003d$9.99, Description\u003dA red light isn\u0027t the desired state in testing but it sure helps when riding})","duration":4239,"startTime":"2021-12-22T04:12:13.710820210Z[Etc/UTC]","screenshots":[{"screenshot":"05d9d773ffb21de266a52191e31a4239fa59cd79458b95893accfe29e84e64ff.png","timeStamp":1640146337949}],"result":"SUCCESS","precondition":false,"level":0,"lineNumber":51,"children":[{"number":12,"description":"Given Colin has logged onto the application","duration":45,"startTime":"2021-12-22T04:12:14.271785793Z[Etc/UTC]","screenshots":[{"screenshot":"d508765a4a5bf8da1a6097a20f84cac5799a28ae3c8ee226ec337bf91493d23f.png","timeStamp":1640146334317}],"result":"SUCCESS","precondition":false,"level":1},{"number":13,"description":"Given Colin is browsing the product catalog","duration":1301,"startTime":"2021-12-22T04:12:14.318120423Z[Etc/UTC]","screenshots":[{"screenshot":"1bd1268f1e1be5f3bf96bd82ecbea1d53f437139494bd2415be950dd44c0cc85.png","timeStamp":1640146335619}],"result":"SUCCESS","precondition":false,"level":1,"children":[{"number":14,"description":"Colin opens the https://www.saucedemo.com/inventory.html","duration":913,"startTime":"2021-12-22T04:12:14.701134482Z[Etc/UTC]","screenshots":[{"screenshot":"1bd1268f1e1be5f3bf96bd82ecbea1d53f437139494bd2415be950dd44c0cc85.png","timeStamp":1640146335614}],"result":"SUCCESS","precondition":false,"level":2}]},{"number":15,"description":"When Colin opens the product details for \"Sauce Labs Bike Light\"","duration":766,"startTime":"2021-12-22T04:12:15.620422683Z[Etc/UTC]","screenshots":[{"screenshot":"1bd1268f1e1be5f3bf96bd82ecbea1d53f437139494bd2415be950dd44c0cc85.png","timeStamp":1640146335622},{"screenshot":"05d9d773ffb21de266a52191e31a4239fa59cd79458b95893accfe29e84e64ff.png","timeStamp":1640146336386}],"result":"SUCCESS","precondition":false,"level":1,"children":[{"number":16,"description":"Colin clicks on the \u0027Sauce Labs Bike Light\u0027 link","duration":756,"startTime":"2021-12-22T04:12:15.626471596Z[Etc/UTC]","screenshots":[{"screenshot":"1bd1268f1e1be5f3bf96bd82ecbea1d53f437139494bd2415be950dd44c0cc85.png","timeStamp":1640146335629},{"screenshot":"05d9d773ffb21de266a52191e31a4239fa59cd79458b95893accfe29e84e64ff.png","timeStamp":1640146336383}],"result":"SUCCESS","precondition":false,"level":2}]},{"number":17,"description":"Then he should see a product with the following details:\n| Name | Price | Description |\n| Sauce Labs Bike Light | $9.99 | A red light isn\u0027t the desired state in testing but it sure helps when riding |","duration":1552,"startTime":"2021-12-22T04:12:16.393622198Z[Etc/UTC]","screenshots":[{"screenshot":"05d9d773ffb21de266a52191e31a4239fa59cd79458b95893accfe29e84e64ff.png","timeStamp":1640146336395},{"screenshot":"05d9d773ffb21de266a52191e31a4239fa59cd79458b95893accfe29e84e64ff.png","timeStamp":1640146337946}],"result":"SUCCESS","precondition":false,"level":1,"children":[{"number":18,"description":"he should see the \u0027inventory_details_name\u0027 element with text value that is equal to (ignoring case): \u003c\"Sauce Labs Bike Light\"\u003e","duration":560,"startTime":"2021-12-22T04:12:16.397203346Z[Etc/UTC]","screenshots":[{"screenshot":"05d9d773ffb21de266a52191e31a4239fa59cd79458b95893accfe29e84e64ff.png","timeStamp":1640146336401},{"screenshot":"05d9d773ffb21de266a52191e31a4239fa59cd79458b95893accfe29e84e64ff.png","timeStamp":1640146336957}],"result":"SUCCESS","precondition":false,"level":2},{"number":19,"description":"he should see the \u0027inventory_details_price\u0027 element with text content that is equal to: \u003c\"$9.99\"\u003e","duration":31,"startTime":"2021-12-22T04:12:16.965546624Z[Etc/UTC]","screenshots":[{"screenshot":"05d9d773ffb21de266a52191e31a4239fa59cd79458b95893accfe29e84e64ff.png","timeStamp":1640146336970},{"screenshot":"05d9d773ffb21de266a52191e31a4239fa59cd79458b95893accfe29e84e64ff.png","timeStamp":1640146336997}],"result":"SUCCESS","precondition":false,"level":2},{"number":20,"description":"he should see the \u0027inventory_details_desc\u0027 element with text value that contains: \u003c[A red light isn\u0027t the desired state in testing but it sure helps when riding]\u003e","duration":931,"startTime":"2021-12-22T04:12:17.004106866Z[Etc/UTC]","screenshots":[{"screenshot":"05d9d773ffb21de266a52191e31a4239fa59cd79458b95893accfe29e84e64ff.png","timeStamp":1640146337907},{"screenshot":"05d9d773ffb21de266a52191e31a4239fa59cd79458b95893accfe29e84e64ff.png","timeStamp":1640146337935}],"result":"SUCCESS","precondition":false,"level":2}]}]},{"number":21,"description":"3: Colin views the details for specific products ({Product Name\u003dSauce Labs Bolt T-Shirt, Price\u003d$15.99, Description\u003dGet your testing superhero})","duration":2582,"startTime":"2021-12-22T04:12:17.973492342Z[Etc/UTC]","screenshots":[{"screenshot":"367078f5be89f466e011e947181411060ef6cecc51458f5699bd9e006a9c7ea2.png","timeStamp":1640146340555}],"result":"SUCCESS","precondition":false,"level":0,"lineNumber":52,"children":[{"number":22,"description":"Given Colin has logged onto the application","duration":564,"startTime":"2021-12-22T04:12:18.592803883Z[Etc/UTC]","screenshots":[{"screenshot":"05d9d773ffb21de266a52191e31a4239fa59cd79458b95893accfe29e84e64ff.png","timeStamp":1640146339156}],"result":"SUCCESS","precondition":false,"level":1},{"number":23,"description":"Given Colin is browsing the product catalog","duration":626,"startTime":"2021-12-22T04:12:19.159656483Z[Etc/UTC]","screenshots":[{"screenshot":"1bd1268f1e1be5f3bf96bd82ecbea1d53f437139494bd2415be950dd44c0cc85.png","timeStamp":1640146339786}],"result":"SUCCESS","precondition":false,"level":1,"children":[{"number":24,"description":"Colin opens the https://www.saucedemo.com/inventory.html","duration":619,"startTime":"2021-12-22T04:12:19.163950121Z[Etc/UTC]","screenshots":[{"screenshot":"1bd1268f1e1be5f3bf96bd82ecbea1d53f437139494bd2415be950dd44c0cc85.png","timeStamp":1640146339783}],"result":"SUCCESS","precondition":false,"level":2}]},{"number":25,"description":"When Colin opens the product details for \"Sauce Labs Bolt T-Shirt\"","duration":384,"startTime":"2021-12-22T04:12:19.786663412Z[Etc/UTC]","screenshots":[{"screenshot":"1bd1268f1e1be5f3bf96bd82ecbea1d53f437139494bd2415be950dd44c0cc85.png","timeStamp":1640146339788},{"screenshot":"367078f5be89f466e011e947181411060ef6cecc51458f5699bd9e006a9c7ea2.png","timeStamp":1640146340171}],"result":"SUCCESS","precondition":false,"level":1,"children":[{"number":26,"description":"Colin clicks on the \u0027Sauce Labs Bolt T-Shirt\u0027 link","duration":371,"startTime":"2021-12-22T04:12:19.789595770Z[Etc/UTC]","screenshots":[{"screenshot":"1bd1268f1e1be5f3bf96bd82ecbea1d53f437139494bd2415be950dd44c0cc85.png","timeStamp":1640146339791},{"screenshot":"367078f5be89f466e011e947181411060ef6cecc51458f5699bd9e006a9c7ea2.png","timeStamp":1640146340161}],"result":"SUCCESS","precondition":false,"level":2}]},{"number":27,"description":"Then he should see a product with the following details:\n| Name | Price | Description |\n| Sauce Labs Bolt T-Shirt | $15.99 | Get your testing superhero |","duration":382,"startTime":"2021-12-22T04:12:20.171637043Z[Etc/UTC]","screenshots":[{"screenshot":"367078f5be89f466e011e947181411060ef6cecc51458f5699bd9e006a9c7ea2.png","timeStamp":1640146340173},{"screenshot":"367078f5be89f466e011e947181411060ef6cecc51458f5699bd9e006a9c7ea2.png","timeStamp":1640146340553}],"result":"SUCCESS","precondition":false,"level":1,"children":[{"number":28,"description":"he should see the \u0027inventory_details_name\u0027 element with text value that is equal to (ignoring case): \u003c\"Sauce Labs Bolt T-Shirt\"\u003e","duration":27,"startTime":"2021-12-22T04:12:20.174930295Z[Etc/UTC]","screenshots":[{"screenshot":"367078f5be89f466e011e947181411060ef6cecc51458f5699bd9e006a9c7ea2.png","timeStamp":1640146340177},{"screenshot":"367078f5be89f466e011e947181411060ef6cecc51458f5699bd9e006a9c7ea2.png","timeStamp":1640146340202}],"result":"SUCCESS","precondition":false,"level":2},{"number":29,"description":"he should see the \u0027inventory_details_price\u0027 element with text content that is equal to: \u003c\"$15.99\"\u003e","duration":309,"startTime":"2021-12-22T04:12:20.206430540Z[Etc/UTC]","screenshots":[{"screenshot":"367078f5be89f466e011e947181411060ef6cecc51458f5699bd9e006a9c7ea2.png","timeStamp":1640146340208},{"screenshot":"367078f5be89f466e011e947181411060ef6cecc51458f5699bd9e006a9c7ea2.png","timeStamp":1640146340516}],"result":"SUCCESS","precondition":false,"level":2},{"number":30,"description":"he should see the \u0027inventory_details_desc\u0027 element with text value that contains: \u003c[Get your testing superhero]\u003e","duration":27,"startTime":"2021-12-22T04:12:20.522374969Z[Etc/UTC]","screenshots":[{"screenshot":"367078f5be89f466e011e947181411060ef6cecc51458f5699bd9e006a9c7ea2.png","timeStamp":1640146340524},{"screenshot":"367078f5be89f466e011e947181411060ef6cecc51458f5699bd9e006a9c7ea2.png","timeStamp":1640146340550}],"result":"SUCCESS","precondition":false,"level":2}]}]},{"number":31,"description":"4: Colin views the details for specific products ({Product Name\u003dSauce Labs Fleece Jacket, Price\u003d$49.99, Description\u003da midweight quarter-zip fleece jacket})","duration":2058,"startTime":"2021-12-22T04:12:20.575999393Z[Etc/UTC]","screenshots":[{"screenshot":"ce0cd0c0add9c1ecf74dfa2cb8c59d468b896e31252540177944592984065223.png","timeStamp":1640146342634}],"result":"SUCCESS","precondition":false,"level":0,"lineNumber":53,"children":[{"number":32,"description":"Given Colin has logged onto the application","duration":44,"startTime":"2021-12-22T04:12:20.880415889Z[Etc/UTC]","screenshots":[{"screenshot":"367078f5be89f466e011e947181411060ef6cecc51458f5699bd9e006a9c7ea2.png","timeStamp":1640146340925}],"result":"SUCCESS","precondition":false,"level":1},{"number":33,"description":"Given Colin is browsing the product catalog","duration":881,"startTime":"2021-12-22T04:12:20.925555736Z[Etc/UTC]","screenshots":[{"screenshot":"1bd1268f1e1be5f3bf96bd82ecbea1d53f437139494bd2415be950dd44c0cc85.png","timeStamp":1640146341806}],"result":"SUCCESS","precondition":false,"level":1,"children":[{"number":34,"description":"Colin opens the https://www.saucedemo.com/inventory.html","duration":874,"startTime":"2021-12-22T04:12:20.928836389Z[Etc/UTC]","screenshots":[{"screenshot":"1bd1268f1e1be5f3bf96bd82ecbea1d53f437139494bd2415be950dd44c0cc85.png","timeStamp":1640146341803}],"result":"SUCCESS","precondition":false,"level":2}]},{"number":35,"description":"When Colin opens the product details for \"Sauce Labs Fleece Jacket\"","duration":423,"startTime":"2021-12-22T04:12:21.807513376Z[Etc/UTC]","screenshots":[{"screenshot":"1bd1268f1e1be5f3bf96bd82ecbea1d53f437139494bd2415be950dd44c0cc85.png","timeStamp":1640146341809},{"screenshot":"ce0cd0c0add9c1ecf74dfa2cb8c59d468b896e31252540177944592984065223.png","timeStamp":1640146342231}],"result":"SUCCESS","precondition":false,"level":1,"children":[{"number":36,"description":"Colin clicks on the \u0027Sauce Labs Fleece Jacket\u0027 link","duration":411,"startTime":"2021-12-22T04:12:21.816348948Z[Etc/UTC]","screenshots":[{"screenshot":"1bd1268f1e1be5f3bf96bd82ecbea1d53f437139494bd2415be950dd44c0cc85.png","timeStamp":1640146341818},{"screenshot":"ce0cd0c0add9c1ecf74dfa2cb8c59d468b896e31252540177944592984065223.png","timeStamp":1640146342228}],"result":"SUCCESS","precondition":false,"level":2}]},{"number":37,"description":"Then he should see a product with the following details:\n| Name | Price | Description |\n| Sauce Labs Fleece Jacket | $49.99 | a midweight quarter-zip fleece jacket |","duration":400,"startTime":"2021-12-22T04:12:22.231809123Z[Etc/UTC]","screenshots":[{"screenshot":"ce0cd0c0add9c1ecf74dfa2cb8c59d468b896e31252540177944592984065223.png","timeStamp":1640146342233},{"screenshot":"ce0cd0c0add9c1ecf74dfa2cb8c59d468b896e31252540177944592984065223.png","timeStamp":1640146342632}],"result":"SUCCESS","precondition":false,"level":1,"children":[{"number":38,"description":"he should see the \u0027inventory_details_name\u0027 element with text value that is equal to (ignoring case): \u003c\"Sauce Labs Fleece Jacket\"\u003e","duration":24,"startTime":"2021-12-22T04:12:22.243456954Z[Etc/UTC]","screenshots":[{"screenshot":"ce0cd0c0add9c1ecf74dfa2cb8c59d468b896e31252540177944592984065223.png","timeStamp":1640146342246},{"screenshot":"ce0cd0c0add9c1ecf74dfa2cb8c59d468b896e31252540177944592984065223.png","timeStamp":1640146342268}],"result":"SUCCESS","precondition":false,"level":2},{"number":39,"description":"he should see the \u0027inventory_details_price\u0027 element with text content that is equal to: \u003c\"$49.99\"\u003e","duration":332,"startTime":"2021-12-22T04:12:22.269501676Z[Etc/UTC]","screenshots":[{"screenshot":"ce0cd0c0add9c1ecf74dfa2cb8c59d468b896e31252540177944592984065223.png","timeStamp":1640146342271},{"screenshot":"ce0cd0c0add9c1ecf74dfa2cb8c59d468b896e31252540177944592984065223.png","timeStamp":1640146342602}],"result":"SUCCESS","precondition":false,"level":2},{"number":40,"description":"he should see the \u0027inventory_details_desc\u0027 element with text value that contains: \u003c[a midweight quarter-zip fleece jacket]\u003e","duration":25,"startTime":"2021-12-22T04:12:22.604234921Z[Etc/UTC]","screenshots":[{"screenshot":"ce0cd0c0add9c1ecf74dfa2cb8c59d468b896e31252540177944592984065223.png","timeStamp":1640146342606},{"screenshot":"ce0cd0c0add9c1ecf74dfa2cb8c59d468b896e31252540177944592984065223.png","timeStamp":1640146342629}],"result":"SUCCESS","precondition":false,"level":2}]}]}],"userStory":{"id":"browse-the-catalog","storyName":"Browse the catalog","displayName":"Browse the catalog","path":"catalog/browse_catalog.feature","type":"feature"},"featureTag":{"name":"Catalog/Browse the catalog","type":"feature","displayName":"Catalog/Browse the catalog"},"title":"Colin views the details for specific products","description":"","backgroundTitle":"","backgroundDescription":"","tags":[{"name":"singlebrowser","type":"tag","displayName":"singlebrowser"},{"name":"Catalog/Browse the catalog","type":"feature","displayName":"Browse the catalog"},{"name":"Catalog","type":"capability","displayName":"Catalog"}],"startTime":"2021-12-22T04:12:09.502032333Z[Etc/UTC]","duration":13132,"rule":{"name":"Customer should be able to view product details for a particular product","description":""},"projectKey":"","sessionId":"ac3764940c31db29899550090ce66270","driver":"chrome:colin","isManualTestingUpToDate":false,"dataTable":{"headers":["Product Name","Price","Description"],"rows":[{"values":["Sauce Labs Backpack","$29.99","carry.allTheThings()"],"lineNumber":50,"result":"SUCCESS"},{"values":["Sauce Labs Bike Light","$9.99","A red light isn\u0027t the desired state in testing but it sure helps when riding"],"lineNumber":51,"result":"SUCCESS"},{"values":["Sauce Labs Bolt T-Shirt","$15.99","Get your testing superhero"],"lineNumber":52,"result":"SUCCESS"},{"values":["Sauce Labs Fleece Jacket","$49.99","a midweight quarter-zip fleece jacket"],"lineNumber":53,"result":"SUCCESS"}],"predefinedRows":true,"scenarioOutline":"Given Colin is browsing the product catalog\n\rWhen Colin opens the product details for \"\u003cProduct Name\u003e\"\n\rThen he should see a product with the following details:\n\r","dataSetDescriptors":[{"startRow":0,"rowCount":0,"name":"","description":""}]},"manual":false,"testSource":"Cucumber","actors":[{"name":"Colin","can":["browse the web"]}],"result":"SUCCESS","scenarioOutline":"Given Colin is browsing the product catalog\nWhen Colin opens the product details for \"\u003cProduct Name\u003e\"\nThen he should see a product with the following details:\n|Name | Price | Description|\n|\u003cProduct Name\u003e | \u003cPrice\u003e | \u003cDescription\u003e|"}