{"name":"Sort products","id":"browse-the-catalog;sort-products","testSteps":[{"number":1,"description":"1: Sort products ({Sort Order\u003dPrice (low to high), First Product\u003dSauce Labs Onesie})","duration":3163,"startTime":"2021-12-22T04:01:18.384263420Z[Etc/UTC]","screenshots":[{"screenshot":"ce0cd0c0add9c1ecf74dfa2cb8c59d468b896e31252540177944592984065223.png","timeStamp":1640145678825},{"screenshot":"74d5a40e3e5e5007b1a52fb6166e0f3a2345589a31a6b1e689c8608db86fdb61.png","timeStamp":1640145681548}],"result":"SUCCESS","precondition":false,"level":0,"lineNumber":63,"children":[{"number":2,"description":"Given Colin has logged onto the application","duration":645,"startTime":"2021-12-22T04:01:18.829643593Z[Etc/UTC]","screenshots":[{"screenshot":"ce0cd0c0add9c1ecf74dfa2cb8c59d468b896e31252540177944592984065223.png","timeStamp":1640145678832},{"screenshot":"ce0cd0c0add9c1ecf74dfa2cb8c59d468b896e31252540177944592984065223.png","timeStamp":1640145679474}],"result":"SUCCESS","precondition":false,"level":1},{"number":3,"description":"Given Colin is browsing the product catalog","duration":1158,"startTime":"2021-12-22T04:01:19.476026479Z[Etc/UTC]","screenshots":[{"screenshot":"ce0cd0c0add9c1ecf74dfa2cb8c59d468b896e31252540177944592984065223.png","timeStamp":1640145679478},{"screenshot":"1bd1268f1e1be5f3bf96bd82ecbea1d53f437139494bd2415be950dd44c0cc85.png","timeStamp":1640145680634}],"result":"SUCCESS","precondition":false,"level":1,"children":[{"number":4,"description":"Colin opens the https://www.saucedemo.com/inventory.html","duration":1149,"startTime":"2021-12-22T04:01:19.480966269Z[Etc/UTC]","screenshots":[{"screenshot":"ce0cd0c0add9c1ecf74dfa2cb8c59d468b896e31252540177944592984065223.png","timeStamp":1640145679501},{"screenshot":"1bd1268f1e1be5f3bf96bd82ecbea1d53f437139494bd2415be950dd44c0cc85.png","timeStamp":1640145680630}],"result":"SUCCESS","precondition":false,"level":2}]},{"number":5,"description":"When he filters the products by Price (low to high)","duration":514,"startTime":"2021-12-22T04:01:20.635324355Z[Etc/UTC]","screenshots":[{"screenshot":"1bd1268f1e1be5f3bf96bd82ecbea1d53f437139494bd2415be950dd44c0cc85.png","timeStamp":1640145680637},{"screenshot":"74d5a40e3e5e5007b1a52fb6166e0f3a2345589a31a6b1e689c8608db86fdb61.png","timeStamp":1640145681149}],"result":"SUCCESS","precondition":false,"level":1,"children":[{"number":6,"description":"he selects Price (low to high) on \u0027product_sort_container\u0027 dropdown","duration":500,"startTime":"2021-12-22T04:01:20.645840463Z[Etc/UTC]","screenshots":[{"screenshot":"1bd1268f1e1be5f3bf96bd82ecbea1d53f437139494bd2415be950dd44c0cc85.png","timeStamp":1640145680649},{"screenshot":"74d5a40e3e5e5007b1a52fb6166e0f3a2345589a31a6b1e689c8608db86fdb61.png","timeStamp":1640145681145}],"result":"SUCCESS","precondition":false,"level":2}]},{"number":7,"description":"Then the first product displayed should be Sauce Labs Onesie","duration":44,"startTime":"2021-12-22T04:01:21.150270043Z[Etc/UTC]","screenshots":[{"screenshot":"74d5a40e3e5e5007b1a52fb6166e0f3a2345589a31a6b1e689c8608db86fdb61.png","timeStamp":1640145681152},{"screenshot":"74d5a40e3e5e5007b1a52fb6166e0f3a2345589a31a6b1e689c8608db86fdb61.png","timeStamp":1640145681194}],"result":"SUCCESS","precondition":false,"level":1,"children":[{"number":8,"description":"he should see text of the \u0027inventory_item_name\u0027 element that is equal to: \u003c\"Sauce Labs Onesie\"\u003e","duration":35,"startTime":"2021-12-22T04:01:21.154939613Z[Etc/UTC]","screenshots":[{"screenshot":"74d5a40e3e5e5007b1a52fb6166e0f3a2345589a31a6b1e689c8608db86fdb61.png","timeStamp":1640145681158},{"screenshot":"74d5a40e3e5e5007b1a52fb6166e0f3a2345589a31a6b1e689c8608db86fdb61.png","timeStamp":1640145681190}],"result":"SUCCESS","precondition":false,"level":2}]}]},{"number":9,"description":"2: Sort products ({Sort Order\u003dPrice (high to low), First Product\u003dSauce Labs Fleece Jacket})","duration":2009,"startTime":"2021-12-22T04:01:21.560406068Z[Etc/UTC]","screenshots":[{"screenshot":"af103d63f702fdb26e5366fa45508451a9afbfb925491b4b2f08bb1930aced51.png","timeStamp":1640145683569}],"result":"SUCCESS","precondition":false,"level":0,"lineNumber":64,"children":[{"number":10,"description":"Given Colin has logged onto the application","duration":403,"startTime":"2021-12-22T04:01:21.564739218Z[Etc/UTC]","screenshots":[{"screenshot":"74d5a40e3e5e5007b1a52fb6166e0f3a2345589a31a6b1e689c8608db86fdb61.png","timeStamp":1640145681968}],"result":"SUCCESS","precondition":false,"level":1},{"number":11,"description":"Given Colin is browsing the product catalog","duration":711,"startTime":"2021-12-22T04:01:21.969209316Z[Etc/UTC]","screenshots":[{"screenshot":"1bd1268f1e1be5f3bf96bd82ecbea1d53f437139494bd2415be950dd44c0cc85.png","timeStamp":1640145682680}],"result":"SUCCESS","precondition":false,"level":1,"children":[{"number":12,"description":"Colin opens the https://www.saucedemo.com/inventory.html","duration":702,"startTime":"2021-12-22T04:01:21.974097498Z[Etc/UTC]","screenshots":[{"screenshot":"1bd1268f1e1be5f3bf96bd82ecbea1d53f437139494bd2415be950dd44c0cc85.png","timeStamp":1640145682676}],"result":"SUCCESS","precondition":false,"level":2}]},{"number":13,"description":"When he filters the products by Price (high to low)","duration":486,"startTime":"2021-12-22T04:01:22.680925286Z[Etc/UTC]","screenshots":[{"screenshot":"1bd1268f1e1be5f3bf96bd82ecbea1d53f437139494bd2415be950dd44c0cc85.png","timeStamp":1640145682683},{"screenshot":"af103d63f702fdb26e5366fa45508451a9afbfb925491b4b2f08bb1930aced51.png","timeStamp":1640145683167}],"result":"SUCCESS","precondition":false,"level":1,"children":[{"number":14,"description":"he selects Price (high to low) on \u0027product_sort_container\u0027 dropdown","duration":475,"startTime":"2021-12-22T04:01:22.685064425Z[Etc/UTC]","screenshots":[{"screenshot":"1bd1268f1e1be5f3bf96bd82ecbea1d53f437139494bd2415be950dd44c0cc85.png","timeStamp":1640145682688},{"screenshot":"af103d63f702fdb26e5366fa45508451a9afbfb925491b4b2f08bb1930aced51.png","timeStamp":1640145683160}],"result":"SUCCESS","precondition":false,"level":2}]},{"number":15,"description":"Then the first product displayed should be Sauce Labs Fleece Jacket","duration":398,"startTime":"2021-12-22T04:01:23.168275477Z[Etc/UTC]","screenshots":[{"screenshot":"af103d63f702fdb26e5366fa45508451a9afbfb925491b4b2f08bb1930aced51.png","timeStamp":1640145683170},{"screenshot":"af103d63f702fdb26e5366fa45508451a9afbfb925491b4b2f08bb1930aced51.png","timeStamp":1640145683566}],"result":"SUCCESS","precondition":false,"level":1,"children":[{"number":16,"description":"he should see text of the \u0027inventory_item_name\u0027 element that is equal to: \u003c\"Sauce Labs Fleece Jacket\"\u003e","duration":31,"startTime":"2021-12-22T04:01:23.176261139Z[Etc/UTC]","screenshots":[{"screenshot":"af103d63f702fdb26e5366fa45508451a9afbfb925491b4b2f08bb1930aced51.png","timeStamp":1640145683179},{"screenshot":"af103d63f702fdb26e5366fa45508451a9afbfb925491b4b2f08bb1930aced51.png","timeStamp":1640145683207}],"result":"SUCCESS","precondition":false,"level":2}]}]},{"number":17,"description":"3: Sort products ({Sort Order\u003dName (A to Z), First Product\u003dSauce Labs Backpack})","duration":1636,"startTime":"2021-12-22T04:01:23.576295280Z[Etc/UTC]","screenshots":[{"screenshot":"1bd1268f1e1be5f3bf96bd82ecbea1d53f437139494bd2415be950dd44c0cc85.png","timeStamp":1640145685212}],"result":"SUCCESS","precondition":false,"level":0,"lineNumber":65,"children":[{"number":18,"description":"Given Colin has logged onto the application","duration":404,"startTime":"2021-12-22T04:01:23.580401918Z[Etc/UTC]","screenshots":[{"screenshot":"af103d63f702fdb26e5366fa45508451a9afbfb925491b4b2f08bb1930aced51.png","timeStamp":1640145683984}],"result":"SUCCESS","precondition":false,"level":1},{"number":19,"description":"Given Colin is browsing the product catalog","duration":729,"startTime":"2021-12-22T04:01:23.985984179Z[Etc/UTC]","screenshots":[{"screenshot":"1bd1268f1e1be5f3bf96bd82ecbea1d53f437139494bd2415be950dd44c0cc85.png","timeStamp":1640145684713}],"result":"SUCCESS","precondition":false,"level":1,"children":[{"number":20,"description":"Colin opens the https://www.saucedemo.com/inventory.html","duration":718,"startTime":"2021-12-22T04:01:23.991271485Z[Etc/UTC]","screenshots":[{"screenshot":"1bd1268f1e1be5f3bf96bd82ecbea1d53f437139494bd2415be950dd44c0cc85.png","timeStamp":1640145684709}],"result":"SUCCESS","precondition":false,"level":2}]},{"number":21,"description":"When he filters the products by Name (A to Z)","duration":451,"startTime":"2021-12-22T04:01:24.716909861Z[Etc/UTC]","screenshots":[{"screenshot":"1bd1268f1e1be5f3bf96bd82ecbea1d53f437139494bd2415be950dd44c0cc85.png","timeStamp":1640145684719},{"screenshot":"1bd1268f1e1be5f3bf96bd82ecbea1d53f437139494bd2415be950dd44c0cc85.png","timeStamp":1640145685168}],"result":"SUCCESS","precondition":false,"level":1,"children":[{"number":22,"description":"he selects Name (A to Z) on \u0027product_sort_container\u0027 dropdown","duration":441,"startTime":"2021-12-22T04:01:24.722245669Z[Etc/UTC]","screenshots":[{"screenshot":"1bd1268f1e1be5f3bf96bd82ecbea1d53f437139494bd2415be950dd44c0cc85.png","timeStamp":1640145684725},{"screenshot":"1bd1268f1e1be5f3bf96bd82ecbea1d53f437139494bd2415be950dd44c0cc85.png","timeStamp":1640145685164}],"result":"SUCCESS","precondition":false,"level":2}]},{"number":23,"description":"Then the first product displayed should be Sauce Labs Backpack","duration":41,"startTime":"2021-12-22T04:01:25.168784300Z[Etc/UTC]","screenshots":[{"screenshot":"1bd1268f1e1be5f3bf96bd82ecbea1d53f437139494bd2415be950dd44c0cc85.png","timeStamp":1640145685171},{"screenshot":"1bd1268f1e1be5f3bf96bd82ecbea1d53f437139494bd2415be950dd44c0cc85.png","timeStamp":1640145685209}],"result":"SUCCESS","precondition":false,"level":1,"children":[{"number":24,"description":"he should see text of the \u0027inventory_item_name\u0027 element that is equal to: \u003c\"Sauce Labs Backpack\"\u003e","duration":33,"startTime":"2021-12-22T04:01:25.172903838Z[Etc/UTC]","screenshots":[{"screenshot":"1bd1268f1e1be5f3bf96bd82ecbea1d53f437139494bd2415be950dd44c0cc85.png","timeStamp":1640145685176},{"screenshot":"1bd1268f1e1be5f3bf96bd82ecbea1d53f437139494bd2415be950dd44c0cc85.png","timeStamp":1640145685206}],"result":"SUCCESS","precondition":false,"level":2}]}]},{"number":25,"description":"4: Sort products ({Sort Order\u003dName (Z to A), First Product\u003dTest.allTheThings() T-Shirt (Red)})","duration":2374,"startTime":"2021-12-22T04:01:25.222953234Z[Etc/UTC]","screenshots":[{"screenshot":"88076c89300312cce46fea59b0df9768576bf3bbc152c6d970f7abe53a243f2e.png","timeStamp":1640145687597}],"result":"SUCCESS","precondition":false,"level":0,"lineNumber":66,"children":[{"number":26,"description":"Given Colin has logged onto the application","duration":40,"startTime":"2021-12-22T04:01:25.596615049Z[Etc/UTC]","screenshots":[{"screenshot":"1bd1268f1e1be5f3bf96bd82ecbea1d53f437139494bd2415be950dd44c0cc85.png","timeStamp":1640145685637}],"result":"SUCCESS","precondition":false,"level":1},{"number":27,"description":"Given Colin is browsing the product catalog","duration":1054,"startTime":"2021-12-22T04:01:25.637784230Z[Etc/UTC]","screenshots":[{"screenshot":"1bd1268f1e1be5f3bf96bd82ecbea1d53f437139494bd2415be950dd44c0cc85.png","timeStamp":1640145686692}],"result":"SUCCESS","precondition":false,"level":1,"children":[{"number":28,"description":"Colin opens the https://www.saucedemo.com/inventory.html","duration":1046,"startTime":"2021-12-22T04:01:25.642286991Z[Etc/UTC]","screenshots":[{"screenshot":"1bd1268f1e1be5f3bf96bd82ecbea1d53f437139494bd2415be950dd44c0cc85.png","timeStamp":1640145686688}],"result":"SUCCESS","precondition":false,"level":2}]},{"number":29,"description":"When he filters the products by Name (Z to A)","duration":493,"startTime":"2021-12-22T04:01:26.693176381Z[Etc/UTC]","screenshots":[{"screenshot":"88076c89300312cce46fea59b0df9768576bf3bbc152c6d970f7abe53a243f2e.png","timeStamp":1640145687187}],"result":"SUCCESS","precondition":false,"level":1,"children":[{"number":30,"description":"he selects Name (Z to A) on \u0027product_sort_container\u0027 dropdown","duration":484,"startTime":"2021-12-22T04:01:26.697105308Z[Etc/UTC]","screenshots":[{"screenshot":"88076c89300312cce46fea59b0df9768576bf3bbc152c6d970f7abe53a243f2e.png","timeStamp":1640145687181}],"result":"SUCCESS","precondition":false,"level":2}]},{"number":31,"description":"Then the first product displayed should be Test.allTheThings() T-Shirt (Red)","duration":406,"startTime":"2021-12-22T04:01:27.187858597Z[Etc/UTC]","screenshots":[{"screenshot":"88076c89300312cce46fea59b0df9768576bf3bbc152c6d970f7abe53a243f2e.png","timeStamp":1640145687190},{"screenshot":"88076c89300312cce46fea59b0df9768576bf3bbc152c6d970f7abe53a243f2e.png","timeStamp":1640145687594}],"result":"SUCCESS","precondition":false,"level":1,"children":[{"number":32,"description":"he should see text of the \u0027inventory_item_name\u0027 element that is equal to: \u003c\"Test.allTheThings() T-Shirt (Red)\"\u003e","duration":33,"startTime":"2021-12-22T04:01:27.195641447Z[Etc/UTC]","screenshots":[{"screenshot":"88076c89300312cce46fea59b0df9768576bf3bbc152c6d970f7abe53a243f2e.png","timeStamp":1640145687198},{"screenshot":"88076c89300312cce46fea59b0df9768576bf3bbc152c6d970f7abe53a243f2e.png","timeStamp":1640145687228}],"result":"SUCCESS","precondition":false,"level":2}]}]}],"userStory":{"id":"browse-the-catalog","storyName":"Browse the catalog","displayName":"Browse the catalog","path":"catalog/browse_catalog.feature","type":"feature"},"featureTag":{"name":"Catalog/Browse the catalog","type":"feature","displayName":"Catalog/Browse the catalog"},"title":"Sort products","description":"","backgroundTitle":"","backgroundDescription":"","tags":[{"name":"singlebrowser","type":"tag","displayName":"singlebrowser"},{"name":"Catalog/Browse the catalog","type":"feature","displayName":"Browse the catalog"},{"name":"Catalog","type":"capability","displayName":"Catalog"}],"startTime":"2021-12-22T04:01:18.381257044Z[Etc/UTC]","duration":9217,"rule":{"name":"Customers should be able to sort product details to see the products they are most interested in","description":""},"projectKey":"","sessionId":"995184d8786c9a6a865406bd09089491","driver":"chrome:colin","isManualTestingUpToDate":false,"dataTable":{"headers":["Sort Order","First Product"],"rows":[{"values":["Price (low to high)","Sauce Labs Onesie"],"lineNumber":63,"result":"SUCCESS"},{"values":["Price (high to low)","Sauce Labs Fleece Jacket"],"lineNumber":64,"result":"SUCCESS"},{"values":["Name (A to Z)","Sauce Labs Backpack"],"lineNumber":65,"result":"SUCCESS"},{"values":["Name (Z to A)","Test.allTheThings() T-Shirt (Red)"],"lineNumber":66,"result":"SUCCESS"}],"predefinedRows":true,"scenarioOutline":"Given Colin is browsing the product catalog\n\rWhen he filters the products by \u003cSort Order\u003e\n\rThen the first product displayed should be \u003cFirst Product\u003e\n\r","dataSetDescriptors":[{"startRow":0,"rowCount":0,"name":"","description":""}]},"manual":false,"testSource":"Cucumber","actors":[{"name":"Colin","can":["browse the web"]}],"result":"SUCCESS","scenarioOutline":"Given Colin is browsing the product catalog\nWhen he filters the products by \u003cSort Order\u003e\nThen the first product displayed should be \u003cFirst Product\u003e"}